{
  "plans": {
    "books": {
      "id": "books",
      "title": "Books",
      "achievement": 365,
      "sessions": []
    },
    "eng": {
      "id": "eng",
      "title": "English",
      "achievement": 365,
      "sessions": []
    },
    "sport": {
      "id": "sport",
      "title": "Sport",
      "achievement": 365,
      "sessions": []
    },
    "programming": {
      "id": "programming",
      "title": "Programming",
      "achievement": 100,
      "sessions": []
    },
    "bicycle": {
      "id": "bicycle",
      "title": "Bicycle",
      "achievement": 100,
      "sessions": []
    }
  }
}
